tide_gpr-0.0.17.dist-info/METADATA
tide_gpr-0.0.17.dist-info/WHEEL
tide_gpr-0.0.17.dist-info/RECORD
tide_gpr-0.0.17.dist-info/licenses/LICENSE
tide_gpr.libs/libgomp-24e2ab19.so.1.0.0
tide/callbacks.py
tide/resampling.py
tide/grid_utils.py
tide/cfl.py
tide/storage.py
tide/padding.py
tide/staggered.py
tide/validation.py
tide/__init__.py
tide/autograd_utils.py
tide/utils.py
tide/backend_utils.py
tide/maxwell.py
tide/wavelets.py
tide/csrc/storage_utils.cu
tide/csrc/maxwell_born.cu
tide/csrc/CMakeLists.txt
tide/csrc/storage_utils.c
tide/csrc/storage_utils.h
tide/csrc/staggered_grid.h
tide/csrc/maxwell.cu
tide/csrc/staggered_grid_3d.h
tide/csrc/common_gpu.h
tide/csrc/common_cpu.h
tide/csrc/maxwell.c
tide/tide/libtide_C.so
