Metadata-Version: 2.2
Name: tide-GPR
Version: 0.0.17
Summary: Torch-based Inversion & Development Engine for electromagnetic wave propagation
Keywords: pytorch,electromagnetic,wave-propagation,maxwell-equations,fdtd,full-waveform-inversion,fwi,geophysics,inverse-problems,cuda
Author-Email: "V.cholerae" <v.cholerae1@gmail.com>
Maintainer-Email: "V.cholerae" <v.cholerae1@gmail.com>
License: MIT
Classifier: Development Status :: 4 - Beta
Classifier: Intended Audience :: Science/Research
Classifier: License :: OSI Approved :: MIT License
Classifier: Programming Language :: Python :: 3
Classifier: Programming Language :: Python :: 3.12
Classifier: Programming Language :: C
Classifier: Programming Language :: C++
Classifier: Topic :: Scientific/Engineering :: Physics
Classifier: Topic :: Scientific/Engineering :: Mathematics
Classifier: Operating System :: POSIX :: Linux
Classifier: Operating System :: Microsoft :: Windows
Classifier: Operating System :: MacOS
Requires-Python: >=3.10
Requires-Dist: matplotlib>=3.10.7
Requires-Dist: numpy>=2.3.5
Requires-Dist: scipy>=1.16.3
Requires-Dist: torch>=2.9.1
Provides-Extra: dev
Requires-Dist: pytest>=7.0; extra == "dev"
Requires-Dist: pytest-cov>=4.0; extra == "dev"
